<?xml version="1.0"?>
<gconf>
	<entry name="timestamp" mtime="1246656637" type="string">
		<stringvalue>1246656637</stringvalue>
	</entry>
	<entry name="type" mtime="1246656637" type="string">
		<stringvalue>802-11-wireless</stringvalue>
	</entry>
	<entry name="uuid" mtime="1246656637" type="string">
		<stringvalue>e2d5ccca-7af4-4217-8bae-f00ad4e7d2b8</stringvalue>
	</entry>
	<entry name="id" mtime="1246656637" type="string">
		<stringvalue>Auto DSTpruebas</stringvalue>
	</entry>
	<entry name="name" mtime="1246656637" type="string">
		<stringvalue>connection</stringvalue>
	</entry>
</gconf>
